{
  "db_name": "PostgreSQL",
  "query": "\n            DELETE FROM \"confirmation_tokens\" \n            WHERE\n                token = $1 and \n                purpose = 'EMAIL_CONFIRMATION' and\n                expires_at > now()\n            RETURNING user_id\n        ",
  "describe": {
    "columns": [
      {
        "ordinal": 0,
        "name": "user_id",
        "type_info": "Uuid"
      }
    ],
    "parameters": {
      "Left": [
        "Text"
      ]
    },
    "nullable": [
      false
    ]
  },
  "hash": "ffdf6e7935e4adc026c32371f2fb5c8a011291c65fe9c505bb78cf933404b31c"
}
